casioplot/__init__.py
casioplot/bg_images/blanck.png
casioplot/bg_images/calculator.png
casioplot/casioplot.py
casioplot/characters.py
casioplot/presets/1080p.toml
casioplot/presets/144p.toml
casioplot/presets/240p.toml
casioplot/presets/360p.toml
casioplot/presets/480p.toml
casioplot/presets/720p.toml
casioplot/presets/default.toml
casioplot/presets/fx-CG50.toml
casioplot/presets/fx-CG50_AU.toml
casioplot/presets/graph_90+e.toml
casioplot/settings.py
casioplot/types.py
casioplot-3.5.1.dist-info/WHEEL
casioplot-3.5.1.dist-info/METADATA
casioplot-3.5.1.dist-info/RECORD
