Metadata-Version: 2.3
Name: casioplot
Version: 3.5.1
Summary: Use casioplot module on a computer
Keywords: casioplot
Author: Uniwix, Miguel Torrinha Pereira
Author-email: Uniwix <uniwixu@gmail.com>, Miguel Torrinha Pereira <miguel.torrinha.pereira+pypi@gmail.com>
License: MIT License
Classifier: License :: OSI Approved :: MIT License
Classifier: Programming Language :: Python
Classifier: Programming Language :: Python :: 3
Requires-Dist: pillow
Requires-Python: >=3.11
Project-URL: Changelog, https://github.com/uniwix/casioplot/releases/latest
Project-URL: Documentation, https://casioplot.readthedocs.io/en/latest/
Project-URL: Homepage, https://github.com/uniwix/casioplot
Project-URL: Issues, https://github.com/uniwix/casioplot/issues
Project-URL: Repository, https://github.com/uniwix/casioplot.git
